text_rewrite_system.py
text_rewrite_system-1.0.2.dist-info/entry_points.txt
text_rewrite_system-1.0.2.dist-info/LICENSE
text_rewrite_system-1.0.2.dist-info/WHEEL
text_rewrite_system-1.0.2.dist-info/METADATA
text_rewrite_system-1.0.2.dist-info/RECORD
