Metadata-Version: 2.1
Name: text_rewrite_system
Version: 1.0.2
Summary: Generates Python functions capable of rewriting text according to pre-defined rules.
Author-email: Sofia Santos <sofiarsantos31@gmail.com>
Classifier: License :: OSI Approved :: MIT License
Requires-Dist: lark
